metapy/__init__.py
metapy/libgcc_s_seh-1.dll
metapy/libmetapy.dll.a
metapy/libstdc++-6.dll
metapy/libwinpthread-1.dll
metapy/metapy.pyd
metapy/zlib1.dll
metapy-0.2.13.dist-info/METADATA
metapy-0.2.13.dist-info/RECORD
metapy-0.2.13.dist-info/WHEEL
metapy-0.2.13.dist-info/top_level.txt
